flowrun/__init__.py
flowrun/action.py
flowrun/flowrun.py
flowrun/handler.py
flowrun/step.py
flowrun/utils.py
flowrun-0.2.0.dist-info/WHEEL
flowrun-0.2.0.dist-info/METADATA
flowrun-0.2.0.dist-info/RECORD
