Metadata-Version: 2.1
Name: flowrun
Version: 0.2.0
Summary: 
Author: pskishere
Author-email: pskishere@gmail.com
Requires-Python: >=3.7,<4.0
Classifier: Programming Language :: Python :: 3
Classifier: Programming Language :: Python :: 3.7
Classifier: Programming Language :: Python :: 3.8
Classifier: Programming Language :: Python :: 3.9
Requires-Dist: requests (>=2.25.0,<3.0.0)
Requires-Dist: sseclient (>=0.0.27,<0.0.28)
